{
  "title": "AI Developer Accelerator Weekly Call",
  "meeting_title": "AI Developer Accelerator Weekly Call",
  "url": "https://fathom.video/calls/261693145",
  "created_at": "2025-03-25T23:21:56Z",
  "scheduled_start_time": "2025-03-25T21:57:21Z",
  "scheduled_end_time": "2025-03-25T22:57:21Z",
  "recording_id": 53794785,
  "recording_start_time": "2025-03-25T21:58:58Z",
  "recording_end_time": "2025-03-25T23:21:36Z",
  "calendar_invitees_domains_type": "one_or_more_external",
  "transcript": null,
  "transcript_language": "en",
  "default_summary": null,
  "action_items": null,
  "calendar_invitees": [
    {
      "name": "Brandon Hancock",
      "email": "brandon@brandonhancock.io",
      "email_domain": "brandonhancock.io",
      "is_external": false,
      "matched_speaker_display_name": null
    }
  ],
  "recorded_by": {
    "name": "Brandon Hancock",
    "email": "brandon@brandonhancock.io",
    "email_domain": "brandonhancock.io",
    "team": null
  },
  "share_url": "https://fathom.video/share/yJo---YjgPYNryDy_8WMBEk-uWx22W41",
  "crm_matches": null
}
